Metadata-Version: 1.0
Name: scalar
Version: 2018.9.10.2016
Summary: Python Matrix library
Home-page: https://github.com/wdbm/scalar
Author: Will Breaden Madden
Author-email: wbm@protonmail.ch
License: GPLv3
Platform: UNKNOWN
